steelsnakes/AU/__init__.py
steelsnakes/AU/checks/uls.py
steelsnakes/AU/data/EA.json
steelsnakes/AU/data/PFC.json
steelsnakes/AU/data/TFB.json
steelsnakes/AU/data/UA.json
steelsnakes/AU/data/UB.json
steelsnakes/AU/data/UC.json
steelsnakes/AU/sections.py
steelsnakes/EU/MEMBERS.md
steelsnakes/EU/__init__.py
steelsnakes/EU/angles.py
steelsnakes/EU/beams.py
steelsnakes/EU/channels.py
steelsnakes/EU/checks/__init__.py
steelsnakes/EU/checks/uls.py
steelsnakes/EU/columns.py
steelsnakes/EU/data/HD.json
steelsnakes/EU/data/HE.json
steelsnakes/EU/data/HL.json
steelsnakes/EU/data/HLZ.json
steelsnakes/EU/data/HP.json
steelsnakes/EU/data/IPE.json
steelsnakes/EU/data/L_EQUAL.json
steelsnakes/EU/data/L_EQUAL_B2B.json
steelsnakes/EU/data/L_UNEQUAL.json
steelsnakes/EU/data/L_UNEQUAL_B2B.json
steelsnakes/EU/data/PFC.json
steelsnakes/EU/data/Sigma.json
steelsnakes/EU/data/UB.json
steelsnakes/EU/data/UBP.json
steelsnakes/EU/data/UC.json
steelsnakes/EU/data/UPE.json
steelsnakes/EU/data/UPN.json
steelsnakes/EU/data/Zed.json
steelsnakes/EU/database.py
steelsnakes/EU/factory.py
steelsnakes/EU/flats.py
steelsnakes/EU/piles.py
steelsnakes/IN/__init__.py
steelsnakes/IN/angles.py
steelsnakes/IN/beams.py
steelsnakes/IN/bearing_piles.py
steelsnakes/IN/channels.py
steelsnakes/IN/checks/Tables.md
steelsnakes/IN/checks/__init__.py
steelsnakes/IN/columns.py
steelsnakes/IN/data/.gitignore
steelsnakes/IN/data/ISEA.json
steelsnakes/IN/data/ISHB.json
steelsnakes/IN/data/ISHT.json
steelsnakes/IN/data/ISJB.json
steelsnakes/IN/data/ISJC.json
steelsnakes/IN/data/ISJT.json
steelsnakes/IN/data/ISLB.json
steelsnakes/IN/data/ISLC.json
steelsnakes/IN/data/ISLT.json
steelsnakes/IN/data/ISMB.json
steelsnakes/IN/data/ISMC.json
steelsnakes/IN/data/ISNT.json
steelsnakes/IN/data/ISST.json
steelsnakes/IN/data/ISUA.json
steelsnakes/IN/data/ISWB.json
steelsnakes/IN/tees.py
steelsnakes/NZ/data/EA.json
steelsnakes/NZ/data/PFC.json
steelsnakes/NZ/data/TFB.json
steelsnakes/NZ/data/UB.json
steelsnakes/NZ/data/UC.json
steelsnakes-0.0.1a7.dist-info/licenses/LICENSE.md
steelsnakes-0.0.1a7.dist-info/WHEEL
steelsnakes-0.0.1a7.dist-info/entry_points.txt
steelsnakes-0.0.1a7.dist-info/METADATA
steelsnakes-0.0.1a7.dist-info/RECORD
