Metadata-Version: 2.4
Name: steelsnakes
Version: 0.0.1a7
Summary: A python library for structural steel.
Author: Wayne Maranga
Author-email: Wayne Maranga <waynemaranga@gmail.com>
License-Expression: GPL-2.0 
License-File: LICENSE.md
Requires-Dist: coverage==7.10.0
Requires-Dist: mkdocs>=1.6.1
Requires-Dist: mkdocs-shadcn==0.9.3
Requires-Dist: mkdocstrings[python]>=0.30.0
Requires-Dist: numpy>=2.3.2
Requires-Dist: pydantic>=2.11.7
Requires-Dist: pymdown-extensions>=10.16.1
Requires-Dist: pytest>=8.4.1
Requires-Dist: pytest-cov>=6.2.1
Requires-Dist: sqlalchemy>=2.0.43
Requires-Python: >=3.11
Project-URL: discussions, https://github.com/waynemaranga/steelsnakes/discussions
Project-URL: documentation, https://steelsnakes.readthedocs.io/en/latest/
Project-URL: homepage, https://github.com/waynemaranga/steelsnakes
Project-URL: issues, https://github.com/waynemaranga/steelsnakes/issues
